nosetalisker
