Metadata-Version: 1.0
Name: nosetalisker
Version: 0.2.1
Summary: UNKNOWN
Home-page: UNKNOWN
Author: Andy McKay
Author-email: andym@mozilla.com
License: BSD
Platform: UNKNOWN
Classifier: Intended Audience :: Developers
Classifier: Natural Language :: English
Classifier: Operating System :: OS Independent
Classifier: Topic :: Software Development :: Testing
